cs/splink.py
cs.splink-20240316.dist-info/METADATA
cs.splink-20240316.dist-info/WHEEL
cs.splink-20240316.dist-info/entry_points.txt
cs.splink-20240316.dist-info/top_level.txt
cs.splink-20240316.dist-info/RECORD
