Metadata-Version: 2.1
Name: cs.splink
Version: 20240316
Summary: Assorted utility functions for working with data downloaded from Selectronics' SP-LINK programme which communicates with their solar inverter controllers.
Author-email: Cameron Simpson <cs@cskk.id.au>
License: GNU General Public License v3 or later (GPLv3+)
Project-URL: URL, https://bitbucket.org/cameron_simpson/css/commits/all
Keywords: python3
Platform: UNKNOWN
Classifier: Development Status :: 3 - Alpha
Classifier: Programming Language :: Python :: 3
Classifier: Intended Audience :: Developers
Classifier: Operating System :: OS Independent
Classifier: Topic :: Software Development :: Libraries :: Python Modules
Classifier: License :: OSI Approved :: GNU General Public License v3 or later (GPLv3+)
Requires-Dist: arrow
Requires-Dist: cs.context >=20240212.1
Requires-Dist: cs.csvutils >=20220606
Requires-Dist: cs.deco >=20240316
Requires-Dist: cs.fs >=20240316
Requires-Dist: cs.fstags >=20240316
Requires-Dist: cs.lex >=20240211
Requires-Dist: cs.logutils >=20230212
Requires-Dist: cs.mplutils >=20230407
Requires-Dist: cs.pfx >=20230604
Requires-Dist: cs.progress >=20230401
Requires-Dist: cs.psutils >=20240211
Requires-Dist: cs.resources >=20240316
Requires-Dist: cs.sqltags >=20240316
Requires-Dist: cs.tagset >=20240316
Requires-Dist: cs.timeseries >=20240316
Requires-Dist: cs.upd >=20240216
Requires-Dist: matplotlib
Requires-Dist: python-dateutil
Requires-Dist: typeguard
